adbkeyeventparser/README.MD
adbkeyeventparser/__init__.py
adbkeyeventparser/requirements.txt
adbkeyeventparser/thirdparty.json
adbkeyeventparser-0.10.dist-info/LICENSE.rst
adbkeyeventparser-0.10.dist-info/METADATA
adbkeyeventparser-0.10.dist-info/WHEEL
adbkeyeventparser-0.10.dist-info/top_level.txt
adbkeyeventparser-0.10.dist-info/RECORD
