Metadata-Version: 2.1
Name: adbkeyeventparser
Version: 0.10
Summary: parses Android keycodes from the official documentation and returns a dictionary containing key information.
Home-page: https://github.com/hansalemaos/adbkeyeventparser
Author: Johannes Fischer
Author-email: aulasparticularesdealemaosp@gmail.com
License: MIT
Keywords: adb,key,event
Classifier: Development Status :: 4 - Beta
Classifier: Programming Language :: Python :: 3 :: Only
Classifier: Programming Language :: Python :: 3.10
Classifier: Topic :: Software Development :: Libraries :: Python Modules
Classifier: Topic :: Utilities
License-File: LICENSE.rst
Requires-Dist: PrettyColorPrinter
Requires-Dist: a-pandas-ex-bs4df-lite
Requires-Dist: lxml
Requires-Dist: pandas
Requires-Dist: requests
